step1/part2 - regfile/regfile.v
module reg_file(IN,OUT1,OUT2,INADDRESS,OUT1ADDRESS,OUT2ADDRESS, WRITE, CLK, RESET);

    input [7:0] IN;
    input [2:0] INADDRESS,OUT1ADDRESS,OUT2ADDRESS;
    input WRITE,CLK,RESET;
    output reg [7:0] OUT1,OUT2;

    reg [7:0] registers [7:0];

    always @(OUT1ADDRESS,OUT2ADDRESS) begin

        #2 OUT1 = registers[OUT1ADDRESS];
        #2 OUT2 = registers[OUT2ADDRESS];
    end

    integer i;

    always @(posedge CLK) begin
        
        if (RESET == 1'b1)
        begin
            #1 for (i = 0; i < 8; i = i +1)
            begin
                registers[i] = 8'b00000000;
            end
        end

        if (WRITE == 1'b1)
        begin

            #1 registers[INADDRESS] = IN;
        end

    end

endmodule

step1/part2 - regfile/testbench.v
/*********************************/
/* CO224 - Computer Architecture */
/* Lab 05 - Part 1				 */
/* Testbench					 */
/* Group - 26					 */
/*********************************/
`include "regfile.v"

module testbench;

	//Input ports for register file
	reg [7:0] WRITEDATA;
	reg [2:0] READREG1, READREG2, WRITEREG;
	reg WRITEENABLE, CLK, RESET;
	
	//Outputs from register file
	wire [7:0] REGOUT1, REGOUT2;
	
	//Instantiating the register file within the testbench module
	reg_file my_reg(WRITEDATA, REGOUT1, REGOUT2, WRITEREG, READREG1, READREG2, WRITEENABLE, CLK, RESET);
	
	
	//Initial block to initialize control signals
	initial
	begin
		CLK = 0;
		RESET = 0;
		WRITEENABLE = 1;
	end
	
	
	//Performing a set of operations on the register file
	initial
	begin
		WRITEREG = 0;		//Writing value 5 to REG0
		WRITEDATA = 5;
		
		READREG1 = 0;		//Reading from REG0
		READREG2 = 3;		//Reading from REG3
		
		#5
		
		WRITEREG = 3;		//Writing value 15 to REG3
		WRITEDATA = 15;
		
		#2
		
		WRITEENABLE = 0;	//Making WRITEENABLE control signal LOW
		
		#3
		
		WRITEREG = 4;		//Writing 27 to REG4 (Does not get written since WRITEENABLE is LOW)
		WRITEDATA = 27;
		
		#5
		
		READREG1 = 4;		//Reading from REG4
		
		#5
		
		READREG1 = 3;		//Reading from REG3
		READREG2 = 0;		//Reading from REG0
		
		#5
		
		RESET = 1;			//Setting RESET signal to HIGH
	end
	
	
	//Always block to maintain clock pulse
	always #2 CLK = !CLK;		//Inverts value of CLK every 2 time units


	//Handling wavedata dumpfile and monitor outputs
	initial
	begin
		$dumpfile("wavedata.vcd");
		$dumpvars(0, my_reg);
		$monitor("TIME = %g OUT1 = %d OUT2 = %d", $time, REGOUT1, REGOUT2);
		#50 $finish;
	end

endmodule

step1/part2 - regfile/wavedata.vcd
$date
	Wed Apr 17 01:29:13 2024
$end
$version
	Icarus Verilog
$end
$timescale
	1s
$end
$scope module testbench $end
$scope module my_reg $end
$var wire 1 ! CLK $end
$var wire 8 " IN [7:0] $end
$var wire 3 # INADDRESS [2:0] $end
$var wire 3 $ OUT1ADDRESS [2:0] $end
$var wire 3 % OUT2ADDRESS [2:0] $end
$var wire 1 & RESET $end
$var wire 1 ' WRITE $end
$var reg 8 ( OUT1 [7:0] $end
$var reg 8 ) OUT2 [7:0] $end
$var integer 32 * i [31:0] $end
$upscope $end
$upscope $end
$enddefinitions $end
$comment Show the parameter values. $end
$dumpall
$end
#0
$dumpvars
bx *
bx )
bx (
1'
0&
b11 %
b0 $
b0 #
b101 "
0!
$end
#2
1!
#4
0!
#5
b1111 "
b11 #
#6
1!
#7
0'
#8
0!
#10
1!
b11011 "
b100 #
#12
0!
#14
1!
#15
b100 $
#16
0!
#18
1!
#19
b1111 )
#20
0!
b0 %
b11 $
#22
b1111 (
1!
#24
b101 )
0!
#25
1&
#26
1!
#27
b1000 *
#28
0!
#30
1!
#31
b1000 *
#32
0!
#34
1!
#35
b1000 *
#36
0!
#38
1!
#39
b1000 *
#40
0!
#42
1!
#43
b1000 *
#44
0!
#46
1!
#47
b1000 *
