step1/part3 - cpu module/group26_lab5_part3/alu.v

module alu(DATA1,DATA2,SELECT,RESULT);

    input [7:0] DATA1,DATA2;
    input [2:0] SELECT;
    output reg [7:0] RESULT;

    wire [7:0] fOut,addOut,andOut,orOut;

    and_1 and_1(DATA1,DATA2,andOut);
    forward_1 forward_1(DATA1,DATA2,fOut);
    add_1 add_1(DATA1,DATA2,addOut);
    or_1 or_1(DATA1,DATA2,orOut);

    always @(SELECT,fOut,addOut,andOut,orOut)
    begin
        case(SELECT)

        3'b000  :RESULT=fOut;
        3'b001  :RESULT=addOut;
        3'b010  :RESULT=andOut;
        3'b011  :RESULT=orOut;

        endcase

    end
endmodule

module add_1(DATA1,DATA2,addOut);

    input [7:0] DATA1,DATA2;
    output reg [7:0] addOut;

    always @(DATA1,DATA2) begin
        #2 addOut = DATA1 + DATA2;
    end
endmodule

module and_1(DATA1,DATA2,andOut);

    input [7:0] DATA1,DATA2;
    output reg [7:0] andOut;

    always @(DATA1,DATA2) begin
        #1 andOut = DATA1 & DATA2;
    end
endmodule

module or_1(DATA1,DATA2,orOut);

    input [7:0] DATA1,DATA2;
    output reg [7:0] orOut;

    always @(DATA1,DATA2) begin
        #1 orOut = DATA1 | DATA2;
    end
endmodule

module forward_1(DATA1,DATA2,fOut);

    input [7:0] DATA1,DATA2;
    output reg [7:0] fOut;

    always @(DATA1,DATA2) begin
        #1 fOut = DATA2;
    end
endmodule

step1/part3 - cpu module/regfile.v
module reg_file(IN,OUT1,OUT2,INADDRESS,OUT1ADDRESS,OUT2ADDRESS, WRITE, CLK, RESET);

    input [7:0] IN;
    input [2:0] INADDRESS,OUT1ADDRESS,OUT2ADDRESS;
    input WRITE,CLK,RESET;
    output reg [7:0] OUT1,OUT2;

    reg [7:0] registers [7:0];

    always @(OUT1ADDRESS,OUT2ADDRESS) begin

        #2
        OUT1 = registers[OUT1ADDRESS];
        OUT2 = registers[OUT2ADDRESS];
    end

    integer i;

    always @(posedge CLK) begin

        $display("%d %d %d %d %d %d %d %d",registers[0],registers[1],registers[2],registers[3],registers[4],registers[5],registers[6],registers[7]);

        
        if (RESET == 1'b1)
        begin
            #1 for (i = 0; i < 8; i = i +1)
            begin
                registers[i] = 8'b00000000;
            end
        end

        if (WRITE == 1'b1)
        begin

            #1 registers[INADDRESS] = IN;
        end

    end

endmodule

step1/part3 - cpu module/group26_lab5_part3/pc.v
// including the alu and reg file
`include "alu.v"
`include "regfile.v"

module cpu(PC, INSTRUCTION, CLK, RESET);

//declaring inputs and outputs
input [31:0] INSTRUCTION;
input CLK,RESET;
output reg [31:0] PC;

//required registers and wires

reg [31:0] PC_reg;
reg [7:0] OPCODE,IMMEDIATE,ALUIN2;
wire [7:0] REGOUT1,REGOUT2,ALURESULT;
reg [2:0] READREG1,READREG2,WRITEREG,ALUOP;
reg WRITEENABLE;

//declaring the ALU and the REGISTER_FILE
reg_file REGITSERS(ALURESULT,REGOUT1,REGOUT2,WRITEREG,READREG1,READREG2,WRITEENABLE,CLK,RESET);
alu ALU(REGOUT1,ALUIN2,ALUOP,ALURESULT);

//updating the program counter if reset=0
always @(posedge CLK)
begin
    #1 PC = PC_reg;
end

//resetting the program counter if reset = 1
always @(posedge CLK)
begin
    if (RESET == 1'b1)
    begin
        #1
        PC = 0;
        PC_reg = 0;
    end
end

//updating the PC_reg
always @(PC)
begin
    #1 PC_reg = PC_reg + 4;
end

always @(INSTRUCTION)
begin
    #1
    // decoding the instruction
OPCODE[7:0] = INSTRUCTION[31:24];
IMMEDIATE[7:0] = INSTRUCTION[7:0];
READREG1[2:0] = INSTRUCTION[10:8];
READREG2[2:0] = INSTRUCTION[2:0];
WRITEREG[2:0] = INSTRUCTION[18:16];


//Load instruction
if (OPCODE == 8'b00000000)
begin
    ALUOP = 3'b000;
    ALUIN2 = IMMEDIATE;
    WRITEENABLE = 1'b1;

end
//move instruction

if (OPCODE == 8'b00000001)
begin
    ALUOP = 3'b000;
    ALUIN2 = REGOUT2;
    WRITEENABLE = 1'b1;

end

//add instruction
if (OPCODE == 8'b00000010)
begin
    ALUOP = 3'b001;
    WRITEENABLE = 1'b1;
    ALUIN2 = REGOUT2;

end

//sub instruction
if (OPCODE == 8'b00000011)
begin
    ALUOP = 3'b001;
    WRITEENABLE = 1'b1;
    ALUIN2 = -REGOUT2;
end

//and instruction
if (OPCODE == 8'b00000100)
begin
    ALUOP = 3'b010;
    WRITEENABLE = 1'b1;
    ALUIN2 = REGOUT2;
end

//or instruction
if (OPCODE == 8'b00000100)
begin
    ALUOP = 3'b011;
    WRITEENABLE = 1'b1;
    ALUIN2 = REGOUT2;
end

end
endmodule

step1/part3 - cpu module/group26_lab5_part3/cpu_tb.v
/*
    * CO224 - Computer Architecture
    * Lab 05 - Part 3
    * cpu_testbench
    * Version 1.0
*/

`include "pc.v"

module Testbench;
    reg CLK, RESET;
    wire [31:0] PC;
    reg [31:0] INSTRUCTION;

    cpu mycpu(PC, INSTRUCTION, CLK, RESET);

    always @ (PC)
    begin
        # 2 // Latency for instruction register
        // Manually written opcodes
        case (PC)
            32'b0000_0000_0000_0000_0000_0000_0000_0000: INSTRUCTION = 32'b00000000_00000100_00000000_00000101; // loadi 4 0x05
            
            32'b0000_0000_0000_0000_0000_0000_0000_0100: INSTRUCTION = 32'b00000000_00000010_00000000_00001001; // loadi 2 0x09

            32'b0000_0000_0000_0000_0000_0000_0000_1000: INSTRUCTION = 32'b00000010_00000110_00000100_00000010; // add 6 4 2

            32'b0000_0000_0000_0000_0000_0000_0000_1100: INSTRUCTION = 32'b00000001_00000000_00000000_00000110; // mov 0 6
            
            32'b0000_0000_0000_0000_0000_0000_0001_0000: INSTRUCTION = 32'b00000000_00000001_00000000_00000001; // loadi 1 0x01
            
            32'b0000_0000_0000_0000_0000_0000_0001_0100: INSTRUCTION = 32'b00000010_00000010_00000010_00000001; // add 2 2 1
        endcase
    end

    initial begin
        // generate files needed to plot the waveform using GTKWave
        $dumpfile("cpu_wavedata1.vcd");
		$dumpvars(0, mycpu);
        
        
        RESET = 1'b0;
        CLK = 1'b0;
        
        // TODO: Reset the CPU (by giving a pulse to RESET signal) to start the program execution
        RESET = 1;
        #6
        RESET = 0;
        // finish simulation after some time
        #100
        $finish;
    end
        
    
    // clock signal generation
    always
        #4 CLK = ~CLK;
    
endmodule

step1/part3 - cpu module/group26_lab5_part3/cpu_wavedata1.vcd
$date
	Sun Apr 28 12:49:42 2024
$end
$version
	Icarus Verilog
$end
$timescale
	1s
$end
$scope module Testbench $end
$scope module mycpu $end
$var wire 1 ! CLK $end
$var wire 32 " INSTRUCTION [31:0] $end
$var wire 1 # RESET $end
$var wire 8 $ REGOUT2 [7:0] $end
$var wire 8 % REGOUT1 [7:0] $end
$var wire 8 & ALURESULT [7:0] $end
$var reg 8 ' ALUIN2 [7:0] $end
$var reg 3 ( ALUOP [2:0] $end
$var reg 8 ) IMMEDIATE [7:0] $end
$var reg 8 * OPCODE [7:0] $end
$var reg 32 + PC [31:0] $end
$var reg 32 , PC_reg [31:0] $end
$var reg 3 - READREG1 [2:0] $end
$var reg 3 . READREG2 [2:0] $end
$var reg 1 / WRITEENABLE $end
$var reg 3 0 WRITEREG [2:0] $end
$scope module ALU $end
$var wire 8 1 DATA2 [7:0] $end
$var wire 3 2 SELECT [2:0] $end
$var wire 8 3 orOut [7:0] $end
$var wire 8 4 fOut [7:0] $end
$var wire 8 5 andOut [7:0] $end
$var wire 8 6 addOut [7:0] $end
$var wire 8 7 DATA1 [7:0] $end
$var reg 8 8 RESULT [7:0] $end
$scope module add_1 $end
$var wire 8 9 DATA2 [7:0] $end
$var wire 8 : DATA1 [7:0] $end
$var reg 8 ; addOut [7:0] $end
$upscope $end
$scope module and_1 $end
$var wire 8 < DATA2 [7:0] $end
$var wire 8 = DATA1 [7:0] $end
$var reg 8 > andOut [7:0] $end
$upscope $end
$scope module forward_1 $end
$var wire 8 ? DATA2 [7:0] $end
$var wire 8 @ DATA1 [7:0] $end
$var reg 8 A fOut [7:0] $end
$upscope $end
$scope module or_1 $end
$var wire 8 B DATA2 [7:0] $end
$var wire 8 C DATA1 [7:0] $end
$var reg 8 D orOut [7:0] $end
$upscope $end
$upscope $end
$scope module REGITSERS $end
$var wire 1 ! CLK $end
$var wire 8 E IN [7:0] $end
$var wire 3 F INADDRESS [2:0] $end
$var wire 3 G OUT1ADDRESS [2:0] $end
$var wire 3 H OUT2ADDRESS [2:0] $end
$var wire 1 # RESET $end
$var wire 1 / WRITE $end
$var reg 8 I OUT1 [7:0] $end
$var reg 8 J OUT2 [7:0] $end
$var integer 32 K i [31:0] $end
$upscope $end
$upscope $end
$upscope $end
$enddefinitions $end
$comment Show the parameter values. $end
$dumpall
$end
#0
$dumpvars
bx K
bx J
bx I
bx H
bx G
bx F
bx E
bx D
bx C
bx B
bx A
bx @
bx ?
bx >
bx =
bx <
bx ;
bx :
bx 9
bx 8
bx 7
bx 6
bx 5
bx 4
bx 3
bx 2
bx 1
bx 0
x/
bx .
bx -
bx ,
bx +
bx *
bx )
bx (
bx '
bx &
bx %
bx $
1#
bx "
0!
$end
#4
1!
#5
b1000 K
b0 ,
b0 +
#6
b100 ,
0#
#7
b1000000000000000101 "
#8
1/
b101 '
b101 1
b101 9
b101 <
b101 ?
b101 B
b0 (
b0 2
b100 0
b100 F
b101 .
b101 H
b0 -
b0 G
b101 )
b0 *
0!
#9
bx1x1 3
bx1x1 D
b0x0x 5
b0x0x >
#10
b101 &
b101 8
b101 E
b101 6
b101 ;
b101 4
b101 A
b0 %
b0 7
b0 :
b0 =
b0 @
b0 C
b0 I
#11
b0 5
b0 >
b101 3
b101 D
#12
b0 $
b0 J
1!
#13
b100 +
#14
b1000 ,
#15
b100000000000001001 "
#16
b1001 '
b1001 1
b1001 9
b1001 <
b1001 ?
b1001 B
b10 0
b10 F
b1 .
b1 H
b1001 )
0!
#17
b1001 3
b1001 D
#18
b1001 &
b1001 8
b1001 E
b1001 4
b1001 A
b1001 6
b1001 ;
#20
1!
#21
b1000 +
#22
b1100 ,
#23
b10000001100000010000000010 "
#24
b0 '
b0 1
b0 9
b0 <
b0 ?
b0 B
b1 (
b1 2
b110 0
b110 F
b10 .
b10 H
b100 -
b100 G
b10 )
b10 *
0!
#25
b0 3
b0 D
#26
b101 &
b101 8
b101 E
b101 6
b101 ;
b0 4
b0 A
b101 %
b101 7
b101 :
b101 =
b101 @
b101 C
b101 I
#27
b101 3
b101 D
#28
b1001 $
b1001 J
1!
#29
b1100 +
#30
b10000 ,
#31
b1000000000000000000000110 "
#32
b0 &
b0 8
b0 E
b1001 '
b1001 1
b1001 9
b1001 <
b1001 ?
b1001 B
b0 (
b0 2
b0 0
b0 F
b110 .
b110 H
b0 -
b0 G
b110 )
b1 *
0!
#33
b1 5
b1 >
b1101 3
b1101 D
#34
b1001 &
b1001 8
b1001 E
b1001 4
b1001 A
b1001 6
b1001 ;
b0 %
b0 7
b0 :
b0 =
b0 @
b0 C
b0 I
#35
b1001 3
b1001 D
b0 5
b0 >
#36
b101 $
b101 J
1!
#37
b10000 +
#38
b10100 ,
#39
b10000000000000001 "
#40
b1 '
b1 1
b1 9
b1 <
b1 ?
b1 B
b1 0
b1 F
b1 .
b1 H
b1 )
b0 *
0!
#41
b1 3
b1 D
#42
b1 &
b1 8
b1 E
b1010 6
b1010 ;
b1 4
b1 A
b1001 %
b1001 7
b1001 :
b1001 =
b1001 @
b1001 C
b1001 I
#43
b1001 3
b1001 D
b1 5
b1 >
#44
b0 $
b0 J
1!
#45
b10100 +
#46
b11000 ,
#47
b10000000100000001000000001 "
#48
b1010 &
b1010 8
b1010 E
b0 '
b0 1
b0 9
b0 <
b0 ?
b0 B
b1 (
b1 2
b10 0
b10 F
b10 -
b10 G
b10 *
0!
#49
b0 5
b0 >
#50
b1001 &
b1001 8
b1001 E
b0 4
b0 A
b1001 6
b1001 ;
#52
b1 $
b1 J
1!
#53
b11000 +
#54
b11100 ,
#56
0!
#60
1!
#61
b11100 +
#62
b100000 ,
#64
0!
#68
1!
#69
b100000 +
#70
b100100 ,
#72
0!
#76
1!
#77
b100100 +
#78
b101000 ,
#80
0!
#84
1!
#85
b101000 +
#86
b101100 ,
#88
0!
#92
1!
#93
b101100 +
#94
b110000 ,
#96
0!
#100
1!
#101
b110000 +
#102
b110100 ,
